{"Nodes":[],"ExecutionTime":"2021-11-17T13:55:46.7697313Z","GenerationTime":"0001-01-01T00:00:00","PluginUserSpecFlowId":"69a20bb2-3199-4936-9e0e-3af590e2050f","CLIUserSpecFlowId":null,"ExecutionResults":[{"ContextType":"Scenario","FeatureFolderPath":"Features","FeatureTitle":"CircusTrain","ScenarioTitle":"Filling up more trains","ScenarioArguments":["150"],"Status":"OK","StepResults":[{"Duration":"00:00:00.0013601","Status":"OK","Error":null,"Outputs":null},{"Duration":"00:00:00.0015646","Status":"OK","Error":null,"Outputs":null},{"Duration":"00:00:00.0016025","Status":"OK","Error":null,"Outputs":null},{"Duration":"00:00:00.0033587","Status":"OK","Error":null,"Outputs":null}],"Outputs":null},{"ContextType":"Scenario","FeatureFolderPath":"Features","FeatureTitle":"CircusTrain","ScenarioTitle":"Filling up more trains","ScenarioArguments":["5"],"Status":"OK","StepResults":[{"Duration":"00:00:00.0000449","Status":"OK","Error":null,"Outputs":null},{"Duration":"00:00:00.0000194","Status":"OK","Error":null,"Outputs":null},{"Duration":"00:00:00.0000177","Status":"OK","Error":null,"Outputs":null},{"Duration":"00:00:00.0000216","Status":"OK","Error":null,"Outputs":null}],"Outputs":null},{"ContextType":"Scenario","FeatureFolderPath":"Features","FeatureTitle":"CircusTrain","ScenarioTitle":"Filling up more trains","ScenarioArguments":["100"],"Status":"OK","StepResults":[{"Duration":"00:00:00.0000342","Status":"OK","Error":null,"Outputs":null},{"Duration":"00:00:00.0000269","Status":"OK","Error":null,"Outputs":null},{"Duration":"00:00:00.0000189","Status":"OK","Error":null,"Outputs":null},{"Duration":"00:00:00.0000221","Status":"OK","Error":null,"Outputs":null}],"Outputs":null},{"ContextType":"Scenario","FeatureFolderPath":"Features","FeatureTitle":"CircusTrain","ScenarioTitle":"Filling up more trains","ScenarioArguments":["200"],"Status":"OK","StepResults":[{"Duration":"00:00:00.0000325","Status":"OK","Error":null,"Outputs":null},{"Duration":"00:00:00.0000357","Status":"OK","Error":null,"Outputs":null},{"Duration":"00:00:00.0000167","Status":"OK","Error":null,"Outputs":null},{"Duration":"00:00:00.0000232","Status":"OK","Error":null,"Outputs":null}],"Outputs":null}],"StepReports":null}